html_text/__init__.py
html_text/html_text.py
html_text-0.6.1.dist-info/LICENSE
html_text-0.6.1.dist-info/METADATA
html_text-0.6.1.dist-info/WHEEL
html_text-0.6.1.dist-info/top_level.txt
html_text-0.6.1.dist-info/RECORD
