Metadata-Version: 2.1
Name: html_text
Version: 0.6.1
Summary: Extract text from HTML
Home-page: https://github.com/zytedata/html-text
Author: Konstantin Lopukhin
Author-email: kostia.lopuhin@gmail.com
License: MIT license
Classifier: Development Status :: 4 - Beta
Classifier: Intended Audience :: Developers
Classifier: License :: OSI Approved :: MIT License
Classifier: Natural Language :: English
Classifier: Programming Language :: Python :: 3
Classifier: Programming Language :: Python :: 3.8
Classifier: Programming Language :: Python :: 3.9
Classifier: Programming Language :: Python :: 3.10
Classifier: Programming Language :: Python :: 3.11
Classifier: Programming Language :: Python :: 3.12
License-File: LICENSE
Requires-Dist: lxml
Requires-Dist: lxml-html-clean
